Metadata-Version: 2.1
Name: odoo-addon-sale_commission_product_criteria
Version: 16.0.2.0.0.1
Summary: Advanced commissions rules
Home-page: https://github.com/OCA/commission
Author: Ilyas, Ooops404, Odoo Community Association (OCA)
Author-email: support@odoo-community.org
License: AGPL-3
Classifier: Programming Language :: Python
Classifier: Framework :: Odoo
Classifier: Framework :: Odoo :: 16.0
Classifier: License :: OSI Approved :: GNU Affero General Public License v3
Requires-Python: >=3.10
Requires-Dist: odoo-addon-sale-commission<16.1dev,>=16.0dev
Requires-Dist: odoo<16.1dev,>=16.0a
